setup.py
nmecpy/ChangePointModel.py
nmecpy/Model.py
nmecpy/StowtModel.py
nmecpy/example.py
nmecpy/hddCddModel.py
nmecpy/nmec.py
nmecpy/towtModel.py
nmecpy.egg-info/PKG-INFO
nmecpy.egg-info/SOURCES.txt
nmecpy.egg-info/dependency_links.txt
nmecpy.egg-info/requires.txt
nmecpy.egg-info/top_level.txt