Metadata-Version: 2.1
Name: nmecpy
Version: 1.3.4
Summary: An implementation of peer-reviewed energy data analysis algorithms in Python for site-specific M&V
Home-page: https://github.com/kW-Labs/nmecpy
Author: Maggie Jacoby, Deter Luu, Devan Johnson
Author-email: dbardin@kw-engineering.com
License: MIT
